myLib/__init__.py
Group45-1.0.dist-info/METADATA
Group45-1.0.dist-info/WHEEL
Group45-1.0.dist-info/top_level.txt
Group45-1.0.dist-info/RECORD
