Metadata-Version: 2.1
Name: Group45
Version: 1.0
Summary: ENSF 338 Final Project
Author: Aser-Ghobara
Author-email: aser.ghobara@ucalgary.ca
